Metadata-Version: 1.1
Name: fluopi
Version: 1.0.0
Summary: Module to manage and analyze time-lapse data obtained with    fluopi equipment
Home-page: https://github.com/SynBioUC/FluoPi
Author: Prosimio
Author-email: innunez@uc.cl
License: MIT
Download-URL: https://github.com/SynBioUC/FluoPi/archive/v1.0.tar.gz
Keywords: DIY Biology,Fluorescence signal,Teaching
Platform: UNKNOWN
Classifier: Development Status :: 3 - Alpha
Classifier: Intended Audience :: Education
Classifier: Intended Audience :: Science/Research
Classifier: Topic :: Education
Classifier: Topic :: Scientific/Engineering :: Artificial Life
Classifier: Topic :: Scientific/Engineering :: Bio-Informatics
Classifier: Topic :: Scientific/Engineering :: Image Recognition
Classifier: Topic :: System :: Hardware
Classifier: License :: OSI Approved :: MIT License
Classifier: Programming Language :: Python :: 2.7
Classifier: Programming Language :: Python :: 3
